eth_dev
