Metadata-Version: 2.1
Name: eth-dev
Version: 0.1.0a3
Summary: Ethereum Development Environment
Home-page: https://github.com/fubuloubu/eth-dev
Author: Bryant Eisenbach
Author-email: fubuloubu@gmail.com
License: MIT
Keywords: ethereum
Platform: UNKNOWN
Classifier: Development Status :: 2 - Pre-Alpha
Classifier: Intended Audience :: Developers
Classifier: License :: OSI Approved :: MIT License
Classifier: Natural Language :: English
Classifier: Programming Language :: Python :: 3
Classifier: Programming Language :: Python :: 3.6
Classifier: Programming Language :: Python :: 3.7
Requires-Python: >=3.6,<4
Provides-Extra: dev
